{
  "additionalProperties": false,
  "properties": {
    "attributes": {
      "additionalProperties": false,
      "properties": {
        "control_implementation_date": {
          "format": "date",
          "type": "string"
        },
        "control_implementation_explanation": {
          "type": "string"
        },
        "control_implementation_status": {
          "enum": [
            "control_implementation_status_yes",
            "control_implementation_status_no",
            "control_implementation_status_partially",
            "control_implementation_status_notApplicable"
          ]
        }
      },
      "type": "object"
    },
    "domains": {
      "description": "The ids of elements of the type domain.",
      "items": {
        "properties": {
          "displayName": {
            "description": "A friendly human readable title of the referenced domain.",
            "type": "string"
          },
          "targetUri": {
            "description": "The resource URL of the referenced domain.",
            "type": "string"
          }
        },
        "required": [
          "targetUri"
        ],
        "type": "object"
      },
      "title": "The list of domains in which this element is present.",
      "type": "array",
      "uniqueItems": true
    },
    "id": {
      "format": "regex",
      "pattern": "[a-fA-F0-9]{8}-[a-fA-F0-9]{4}-[a-fA-F0-9]{4}-[a-fA-F0-9]{4}-[a-fA-F0-9]{12}",
      "title": "The UUID to identify the element",
      "type": "string"
    },
    "references": {
      "items": {
        "properties": {
          "displayName": {
            "description": "A friendly human readable title of the referenced object.",
            "type": "string"
          },
          "targetUri": {
            "description": "The resource URL of the referenced object.",
            "type": "string"
          }
        },
        "required": [
          "targetUri"
        ]
      },
      "type": "array"
    },
    "type": {
      "description": "The name of the type described by this schema.",
      "enum": [
        "control_implementation"
      ]
    }
  },
  "type": "object"
}
